{
  "task": "push_plate_v1",
  "frame_id": "0360",
  "contact_area_radius": 5,
  "human_image": "0360_human.jpg",
  "robot_image": "0360_robot.jpg",
  "image_size": {
    "human": {
      "width": 426,
      "height": 240
    },
    "robot": {
      "width": 426,
      "height": 240
    }
  },
  "human_points": [
    {
      "id": 1,
      "x": 344,
      "y": 131,
      "label": "contact",
      "radius": 5
    }
  ],
  "robot_points": [
    {
      "id": 1,
      "x": 336,
      "y": 120,
      "label": "contact",
      "radius": 5
    }
  ],
  "note": "Coordinates and radius are original image pixel units."
}